json2netcdf/__init__.py
json2netcdf/__main__.py
json2netcdf/json2netcdf.py
json2netcdf-1.1.2.dist-info/LICENSE
json2netcdf-1.1.2.dist-info/METADATA
json2netcdf-1.1.2.dist-info/WHEEL
json2netcdf-1.1.2.dist-info/entry_points.txt
json2netcdf-1.1.2.dist-info/top_level.txt
json2netcdf-1.1.2.dist-info/RECORD
