Metadata-Version: 2.1
Name: json2netcdf
Version: 1.1.2
Summary: Package to convert JSON to NetCDF data
Home-page: https://github.com/samharrison7/json2netcdf
Author: Sam Harrison
Author-email: samharrison.xg@gmail.com
License: UNKNOWN
Project-URL: Bug Tracker, https://github.com/samharrison7/json2netcdf/issues
Platform: UNKNOWN
Classifier: Programming Language :: Python :: 3
Classifier: License :: OSI Approved :: BSD License
Classifier: Operating System :: OS Independent
Requires-Python: >=3.6
License-File: LICENSE
Requires-Dist: numpy
Requires-Dist: netCDF4
